MANIFEST.in
setup.cfg
setup.py
versioneer.py
bin/lsfm
lsfm/__init__.py
lsfm/_version.py
lsfm/camera.py
lsfm/correspond.py
lsfm/io.py
lsfm/landmark.py
lsfm/model.py
lsfm/shading.py
lsfm/visualize.py
lsfm.egg-info/PKG-INFO
lsfm.egg-info/SOURCES.txt
lsfm.egg-info/dependency_links.txt
lsfm.egg-info/requires.txt
lsfm.egg-info/top_level.txt
lsfm/data/__init__.py
lsfm/data/basel.py
lsfm/data/basel_template_metadata.pkl