Metadata-Version: 1.0
Name: lsfm
Version: 1.0.0
Summary: Large Scale Facial Model (LSFM) construction pipeline
Home-page: UNKNOWN
Author: James Booth
Author-email: james.booth08@imperial.ac.uk
License: UNKNOWN
Platform: UNKNOWN
